optimal_data_selector/__init__.py
optimal_data_selector/__version__.py
optimal_data_selector/files.py
optimal_data_selector/image.py
optimal_data_selector/optimal.py
optimal_data_selector/optimal_2.py
optimal_data_selector/sequential.py
optimal_data_selector/text.py
optimal_data_selector/version.py
optimal_data_selector/word.py
optimal_data_selector-1.2.2.dist-info/LICENSE
optimal_data_selector-1.2.2.dist-info/METADATA
optimal_data_selector-1.2.2.dist-info/WHEEL
optimal_data_selector-1.2.2.dist-info/top_level.txt
optimal_data_selector-1.2.2.dist-info/RECORD
